LICENSE
MANIFEST.in
README.txt
setup.py
bin/ftp-gss
bin/login
pykerberos.egg-info/PKG-INFO
pykerberos.egg-info/SOURCES.txt
pykerberos.egg-info/dependency_links.txt
pykerberos.egg-info/top_level.txt
pysrc/kerberos.py
src/base64.c
src/base64.h
src/kerberos.c
src/kerberosbasic.c
src/kerberosbasic.h
src/kerberosgss.c
src/kerberosgss.h
src/kerberospw.c
src/kerberospw.h