Metadata-Version: 1.1
Name: pykerberos
Version: 1.2.1
Summary: High-level interface to Kerberos
Home-page: UNKNOWN
Author: UNKNOWN
Author-email: UNKNOWN
License: ASL 2.0
Platform: UNKNOWN
Classifier: License :: OSI Approved :: Apache Software License
Classifier: Programming Language :: Python :: 2
Classifier: Programming Language :: Python :: 3
Classifier: Topic :: Software Development :: Libraries :: Python Modules
Classifier: Topic :: System :: Systems Administration :: Authentication/Directory
